README.md
setup.py
yaml_to_object.py
yaml_to_object.egg-info/PKG-INFO
yaml_to_object.egg-info/SOURCES.txt
yaml_to_object.egg-info/dependency_links.txt
yaml_to_object.egg-info/requires.txt
yaml_to_object.egg-info/top_level.txt